pure_ocean_breeze/__init__.py
pure_ocean_breeze/data/__init__.py
pure_ocean_breeze/data/database.py
pure_ocean_breeze/data/dicts.py
pure_ocean_breeze/data/read_data.py
pure_ocean_breeze/data/tools.py
pure_ocean_breeze/data/write_data.py
pure_ocean_breeze/future_version/__init__.py
pure_ocean_breeze/future_version/half_way.py
pure_ocean_breeze/future_version/in_thoughts.py
pure_ocean_breeze/initialize/__init__.py
pure_ocean_breeze/initialize/initialize.py
pure_ocean_breeze/jason/__init__.py
pure_ocean_breeze/jason/data/__init__.py
pure_ocean_breeze/jason/data/database.py
pure_ocean_breeze/jason/data/dicts.py
pure_ocean_breeze/jason/data/read_data.py
pure_ocean_breeze/jason/data/tools.py
pure_ocean_breeze/jason/labor/__init__.py
pure_ocean_breeze/jason/labor/comment.py
pure_ocean_breeze/jason/labor/process.py
pure_ocean_breeze/jason/state/__init__.py
pure_ocean_breeze/jason/state/decorators.py
pure_ocean_breeze/jason/state/homeplace.py
pure_ocean_breeze/jason/state/states.py
pure_ocean_breeze/jason/withs/__init__.py
pure_ocean_breeze/jason/withs/requires.py
pure_ocean_breeze/labor/__init__.py
pure_ocean_breeze/labor/comment.py
pure_ocean_breeze/labor/process.py
pure_ocean_breeze/legacy_version/__init__.py
pure_ocean_breeze/legacy_version/v1/__init__.py
pure_ocean_breeze/legacy_version/v1/initialize.py
pure_ocean_breeze/legacy_version/v1/pure_ocean_breeze.py
pure_ocean_breeze/legacy_version/v1p10/__init__.py
pure_ocean_breeze/legacy_version/v1p10/initialize.py
pure_ocean_breeze/legacy_version/v1p10/pure_ocean_breeze.py
pure_ocean_breeze/legacy_version/v2/__init__.py
pure_ocean_breeze/legacy_version/v2/initialize.py
pure_ocean_breeze/legacy_version/v2/pure_ocean_breeze.py
pure_ocean_breeze/legacy_version/v3p1/__init__.py
pure_ocean_breeze/legacy_version/v3p1/data/__init__.py
pure_ocean_breeze/legacy_version/v3p1/data/database.py
pure_ocean_breeze/legacy_version/v3p1/data/dicts.py
pure_ocean_breeze/legacy_version/v3p1/data/read_data.py
pure_ocean_breeze-5.0.1.dist-info/LICENSE
pure_ocean_breeze-5.0.1.dist-info/METADATA
pure_ocean_breeze-5.0.1.dist-info/WHEEL
pure_ocean_breeze-5.0.1.dist-info/top_level.txt
pure_ocean_breeze-5.0.1.dist-info/RECORD
