Metadata-Version: 2.1
Name: pure_ocean_breeze
Version: 5.0.1
Summary: stock factor test
Home-page: https://github.com/chen-001/pure_ocean_breeze.git
Author: chenzongwei
Author-email: winterwinter999@163.com
License: MIT
Project-URL: Documentation, https://chen-001.github.io/pure_ocean_breeze/
Requires-Python: >=3
License-File: LICENSE
Requires-Dist: pandas <=1.5.3
Requires-Dist: scipy
Requires-Dist: statsmodels
Requires-Dist: plotly
Requires-Dist: pyarrow
Requires-Dist: loguru
Requires-Dist: knockknock
Requires-Dist: dcube
Requires-Dist: tenacity
Requires-Dist: pickledb
Requires-Dist: pymysql
Requires-Dist: sqlalchemy
Requires-Dist: requests
Requires-Dist: bs4
Requires-Dist: wrapt-timeout-decorator
Requires-Dist: pyfinance
Requires-Dist: texttable
Requires-Dist: numpy-ext
Requires-Dist: xpinyin
Requires-Dist: cufflinks
Requires-Dist: clickhouse-sqlalchemy
Requires-Dist: tradetime
Requires-Dist: deprecation
Requires-Dist: questdb ==1.1.0
Requires-Dist: mpire
Requires-Dist: py7zr
Requires-Dist: unrar
Requires-Dist: rarfile
Requires-Dist: chardet
Requires-Dist: psycopg2-binary
Provides-Extra: linux
Requires-Dist: psycopg2-binary ; extra == 'linux'
Provides-Extra: macos
Requires-Dist: psycopg2-binary ; extra == 'macos'
Provides-Extra: windows
Requires-Dist: psycopg2 ; extra == 'windows'
